MANIFEST.in
README.md
httpie_esni_auth.py
setup.py
httpie_esni_auth.egg-info/PKG-INFO
httpie_esni_auth.egg-info/SOURCES.txt
httpie_esni_auth.egg-info/dependency_links.txt
httpie_esni_auth.egg-info/entry_points.txt
httpie_esni_auth.egg-info/not-zip-safe
httpie_esni_auth.egg-info/requires.txt
httpie_esni_auth.egg-info/top_level.txt