Metadata-Version: 1.1
Name: httpie-esni-auth
Version: 1.0.0
Summary: ESNI auth plugin for HTTPie.
Home-page: https://github.com/pd/httpie-esni-auth
Author: Daniel G. Taylor
Author-email: dtaylor@istreamplanet.com
License: Apache2
Download-URL: https://github.com/pd/httpie-esni-auth
Platform: UNKNOWN
Classifier: Development Status :: 4 - Beta
Classifier: Programming Language :: Python
Classifier: Intended Audience :: Developers
Classifier: Environment :: Plugins
Classifier: License :: OSI Approved :: MIT License
Classifier: Topic :: Internet :: WWW/HTTP
Classifier: Topic :: Utilities
